{"is_source_file": true, "format": "CSS", "description": "This file contains a CSS stylesheet defining the visual theme, layout, components, and responsiveness of the frontend web application, with a focus on a minimalist, accessible, and responsive user interface.", "external_files": [], "external_methods": [], "published": [], "classes": [], "methods": [], "calls": [], "search-terms": ["Ocean Professional Minimalist Theme", "CSS variables", "responsive layout", "sidebar styles", "dark theme", "app layout", "buttons", "inputs", "cards", "typography"], "state": 2, "file_id": 5, "knowledge_revision": 90, "git_revision": "162a5cf19fbea8ea8bc6946ef1ede02642afcc0b", "hash": "df94b2dbbf6dccfc49ef1991b2f7928a", "format-version": 4, "code-base-name": "frontend_web_app", "filename": "frontend_web_app/src/App.css", "revision_history": [{"90": "162a5cf19fbea8ea8bc6946ef1ede02642afcc0b"}]}