{"is_source_file": true, "format": "JavaScript (React JSX)", "description": "This is the main application source file for a React web application. It sets up routing, layout, theme toggling, and imports various components used throughout the app, including authentication, dashboard, learning modules, portfolio, mentorship, job tools, and settings.", "external_files": ["./state/AuthContext", "./routes/ProtectedRoute", "./components/common/Sidebar", "./components/common/TopBar", "./components/auth/Login", "./components/auth/Register", "./components/dashboard/DashboardHome", "./components/learning/ModulesList", "./components/learning/ModuleDetail", "./components/learning/LessonViewer", "./components/learning/QuizRunner", "./components/portfolio/PortfolioEditor", "./components/portfolio/PortfolioViewer", "./components/portfolio/Certificates", "./components/mentorship/MentorList", "./components/mentorship/MentorDetail", "./components/mentorship/Booking", "./components/jobtools/ResumeBuilder", "./components/jobtools/InterviewSimulator", "./components/jobtools/SoftSkills", "./components/settings/Settings", "react", "react-router-dom"], "external_methods": ["React.useState", "React.useEffect", "React.useMemo", "BrowserRouter", "Routes", "Route", "Navigate"], "published": ["App"], "classes": [], "methods": [{"name": "App()", "description": "Main functional component initializing theme state, layout, and routing structure. Implements theme toggling and navigation setup with protected and public routes.", "scope": "", "scopeKind": ""}, {"name": "LayoutWrapper({ children })", "scope": "App", "scopeKind": "function", "description": "unavailable"}], "calls": ["document.documentElement.setAttribute", "useState", "useEffect", "useMemo", "React.createElement", "React.Fragment"], "search-terms": ["React Router setup", "ProtectedRoute", "Theme toggle", "LayoutWrapper", "AuthProvider", "DashboardHome", "ModulesList", "PortfolioViewer", "MentorList", "ResumeBuilder", "Settings"], "state": 2, "file_id": 7, "knowledge_revision": 41, "git_revision": "326696a3e45d3882f2bb1988be3d1b916775e6a3", "revision_history": [{"23": "326696a3e45d3882f2bb1988be3d1b916775e6a3"}, {"41": "326696a3e45d3882f2bb1988be3d1b916775e6a3"}], "ctags": [{"_type": "tag", "name": "App", "path": "/home/kavia/workspace/code-generation/careerskill-bridge-264016-264026/frontend_web_app/src/App.js", "pattern": "/^export default function App() {$/", "language": "JavaScript", "kind": "function", "signature": "()"}, {"_type": "tag", "name": "LayoutWrapper", "path": "/home/kavia/workspace/code-generation/careerskill-bridge-264016-264026/frontend_web_app/src/App.js", "pattern": "/^    return function LayoutWrapper({ children }) {$/", "language": "JavaScript", "kind": "function", "signature": "({ children })", "scope": "App", "scopeKind": "function"}], "hash": "7c2f3b8a2e8c51ea27e5763369dc65d7", "format-version": 4, "code-base-name": "frontend_web_app", "filename": "frontend_web_app/src/App.js"}